{
  "routes": [
    {
      "method": "GET",
      "path": "/student-invites",
      "handler": "student-invite.find",
      "config": {
        "policies": []
      }
    },
    {
      "method": "GET",
      "path": "/student-invites/count",
      "handler": "student-invite.count",
      "config": {
        "policies": []
      }
    },
    {
      "method": "GET",
      "path": "/student-invites/:id",
      "handler": "student-invite.findOne",
      "config": {
        "policies": []
      }
    },
    {
      "method": "POST",
      "path": "/student-invites",
      "handler": "student-invite.create",
      "config": {
        "policies": []
      }
    },
    {
      "method": "PUT",
      "path": "/student-invites/:id",
      "handler": "student-invite.update",
      "config": {
        "policies": []
      }
    },
    {
      "method": "DELETE",
      "path": "/student-invites/:id",
      "handler": "student-invite.delete",
      "config": {
        "policies": []
      }
    }
  ]
}
